cursor_pagination.py
django_cursor_pagination_dtkav-0.1.7.dist-info/DESCRIPTION.rst
django_cursor_pagination_dtkav-0.1.7.dist-info/METADATA
django_cursor_pagination_dtkav-0.1.7.dist-info/RECORD
django_cursor_pagination_dtkav-0.1.7.dist-info/WHEEL
django_cursor_pagination_dtkav-0.1.7.dist-info/metadata.json
django_cursor_pagination_dtkav-0.1.7.dist-info/top_level.txt
