Metadata-Version: 2.0
Name: django-cursor-pagination-dtkav
Version: 0.1.7
Summary: Cursor based pagination for Django
Home-page: https://github.com/dtkav/django-cursor-pagination
Author: Photocrowd, dtkav
Author-email: me@danielgk.com
License: BSD
Platform: UNKNOWN
Classifier: Development Status :: 2 - Pre-Alpha
Classifier: Framework :: Django
Classifier: Intended Audience :: Developers
Classifier: License :: OSI Approved :: BSD License
Classifier: Natural Language :: English
Classifier: Programming Language :: Python :: 2
Classifier: Programming Language :: Python :: 2.7
Classifier: Programming Language :: Python :: 3
Classifier: Programming Language :: Python :: 3.4
Classifier: Programming Language :: Python :: 3.5
Classifier: Programming Language :: Python :: 3.6
Classifier: Programming Language :: Python :: 3.7
